{
  "items": [
    { "name": "9 5 . s o u t h", "img": "https://upload.wikimedia.org/wikipedia/en/7/7d/TheOff-Season.jpeg" },
    { "name": "a m a r i", "img": "https://upload.wikimedia.org/wikipedia/en/7/7d/TheOff-Season.jpeg" },
    { "name": "m y . l i f e (feat. 21 Savage & Morray)", "img": "https://upload.wikimedia.org/wikipedia/en/7/7d/TheOff-Season.jpeg" },
    { "name": "a p p l y i n g . p r e s s u r e", "img": "https://upload.wikimedia.org/wikipedia/en/7/7d/TheOff-Season.jpeg" },
    { "name": "p u n c h i n’ . t h e . c l o c k", "img": "https://upload.wikimedia.org/wikipedia/en/7/7d/TheOff-Season.jpeg" },
    { "name": "1 0 0 . m i l’", "img": "https://upload.wikimedia.org/wikipedia/en/7/7d/TheOff-Season.jpeg" },
    { "name": "p r i d e . i s . t h e . d e v i l (feat. Lil Baby)", "img": "https://upload.wikimedia.org/wikipedia/en/7/7d/TheOff-Season.jpeg" },
    { "name": "l e t . g o . m y . h a n d", "img": "https://upload.wikimedia.org/wikipedia/en/7/7d/TheOff-Season.jpeg" },
    { "name": "i n t e r l u d e", "img": "https://upload.wikimedia.org/wikipedia/en/7/7d/TheOff-Season.jpeg" },
    { "name": "t h e . c l i m b . b a c k", "img": "https://upload.wikimedia.org/wikipedia/en/7/7d/TheOff-Season.jpeg" },
    { "name": "c l o s e", "img": "https://upload.wikimedia.org/wikipedia/en/7/7d/TheOff-Season.jpeg" },
    { "name": "h u n g e r . o n . h i l l s i d e", "img": "https://upload.wikimedia.org/wikipedia/en/7/7d/TheOff-Season.jpeg" }
  ]
}
